arq_scheduler/__init__.py
arq_scheduler/cli.py
arq_scheduler/job_store/__init__.py
arq_scheduler/job_store/base.py
arq_scheduler/job_store/redis.py
arq_scheduler/job_store/sql.py
arq_scheduler/scheduler/__init__.py
arq_scheduler/scheduler/scheduler.py
arq_scheduler/utils/__init__.py
arq_scheduler/utils/logging.py
arq_scheduler-0.0.2.dist-info/METADATA
arq_scheduler-0.0.2.dist-info/WHEEL
arq_scheduler-0.0.2.dist-info/entry_points.txt
arq_scheduler-0.0.2.dist-info/top_level.txt
arq_scheduler-0.0.2.dist-info/RECORD
