Metadata-Version: 2.4
Name: arq-scheduler
Version: 0.0.2
Summary: ARQ Scheduler adds job scheduling capability to ARQ (the Async successor to RQ). Adapted from rq-scheduler
Author-email: Benjamin English <bdenglish@gmail.com>
Project-URL: Homepage, https://github.com/bdenglish/arq-scheduler
Project-URL: Issues, https://github.com/bdenglish/arq-scheduler/issues
Classifier: Programming Language :: Python :: 3
Classifier: Operating System :: OS Independent
Classifier: License :: OSI Approved :: MIT License
Requires-Python: >=3.11
Requires-Dist: arq
Requires-Dist: click
Requires-Dist: crontab
Requires-Dist: freezegun
Requires-Dist: python-dateutil
